Metadata-Version: 2.1
Name: tensorcox
Version: 0.1
Summary: Coxs partial likelihood in Tensorflow
Home-page: https://github.com/alexwjung/TensorCox/archive/v_0.1.tar.gz
Author: awj
Author-email: alexwjung@googlemail.com
License: MIT
Platform: UNKNOWN
